similarnames/__init__.py
similarnames/similarnames.py
similarnames-0.1.7.dist-info/LICENSE
similarnames-0.1.7.dist-info/WHEEL
similarnames-0.1.7.dist-info/METADATA
similarnames-0.1.7.dist-info/RECORD
