Metadata-Version: 2.1
Name: similarnames
Version: 0.1.7
Summary: Library for Standardizing names from a Pandas dataframe
Home-page: https://github.com/paulobrunheroto/similarnames
License: MIT
Author: paulobrunheroto
Author-email: paulobrunheroto@hotmail.com
Requires-Python: >=3.7,<4.0
Classifier: License :: OSI Approved :: MIT License
Classifier: Programming Language :: Python :: 3
Classifier: Programming Language :: Python :: 3.10
Classifier: Programming Language :: Python :: 3.7
Classifier: Programming Language :: Python :: 3.8
Classifier: Programming Language :: Python :: 3.9
Requires-Dist: nltk (>=3.7,<4.0)
Requires-Dist: unidecode (>=1.3.4,<2.0.0)
Project-URL: Repository, https://github.com/paulobrunheroto/similarnames
